urlscan/__init__.py
urlscan/_version.py
urlscan/_version.pyi
urlscan/client.py
urlscan/error.py
urlscan/iterator.py
urlscan/types.py
urlscan/utils.py
urlscan/pro/__init__.py
urlscan/pro/brand.py
urlscan/pro/channel.py
urlscan/pro/datadump.py
urlscan/pro/hostname.py
urlscan/pro/incident.py
urlscan/pro/livescan.py
urlscan/pro/saved_search.py
urlscan/pro/subscription.py
urlscan_python-0.0.2.dist-info/METADATA
urlscan_python-0.0.2.dist-info/WHEEL
urlscan_python-0.0.2.dist-info/licenses/LICENSE
urlscan_python-0.0.2.dist-info/RECORD
