Metadata-Version: 2.4
Name: urlscan-python
Version: 0.0.2
Summary: The official Python API client for urlscan.io
Project-URL: Repository, https://github.com/urlscan/urlscan-python/
Project-URL: Homepage, https://github.com/urlscan/urlscan-python/
Project-URL: Documentation, https://urlscan.github.io/urlscan-python/
Project-URL: Issues, https://github.com/urlscan/urlscan-python/issues/
License-File: LICENSE
Classifier: Programming Language :: Python
Classifier: Programming Language :: Python :: 3.10
Classifier: Programming Language :: Python :: 3.11
Classifier: Programming Language :: Python :: 3.12
Classifier: Programming Language :: Python :: 3.13
Classifier: Programming Language :: Python :: 3.14
Requires-Python: <4.0,>=3.10
Requires-Dist: httpx~=0.27
